highway/__init__.py
highway/ast_utils.py
highway/context.py
highway/driver.py
highway/exceptions.py
highway/result.py
highway/runner.py
highway/task.py
highway-0.1.1.dist-info/licenses/LICENSE
highway-0.1.1.dist-info/METADATA
highway-0.1.1.dist-info/WHEEL
highway-0.1.1.dist-info/top_level.txt
highway-0.1.1.dist-info/RECORD
