Metadata-Version: 2.4
Name: highway
Version: 0.1.1
Summary: Python SDK for Highway Workflow Engine - build durable workflows with simple decorators
Author-email: Highway Team <team@highway.solutions>
License-Expression: Apache-2.0
Project-URL: Homepage, https://highway.solutions
Project-URL: Documentation, https://docs.highway.solutions
Project-URL: Repository, https://github.com/highway/highway-driver
Keywords: workflow,orchestration,highway,durable,execution,sdk
Classifier: Development Status :: 4 - Beta
Classifier: Intended Audience :: Developers
Classifier: Programming Language :: Python :: 3
Classifier: Programming Language :: Python :: 3.11
Classifier: Programming Language :: Python :: 3.12
Classifier: Programming Language :: Python :: 3.13
Classifier: Topic :: Software Development :: Libraries :: Python Modules
Classifier: Topic :: System :: Distributed Computing
Requires-Python: >=3.11
License-File: LICENSE
Requires-Dist: httpx>=0.24.0
Provides-Extra: dev
Requires-Dist: pytest>=7.0; extra == "dev"
Requires-Dist: pytest-asyncio>=0.21; extra == "dev"
Requires-Dist: mypy>=1.0; extra == "dev"
Requires-Dist: ruff>=0.1; extra == "dev"
Dynamic: license-file
